MANIFEST.in
README
setup.py
bin/tcom
pvtk/__init__.py
pvtk/assim.py
pvtk/basics.py
pvtk/morph.py
pvtk/post_morph.py
pvtk.egg-info/PKG-INFO
pvtk.egg-info/SOURCES.txt
pvtk.egg-info/dependency_links.txt
pvtk.egg-info/requires.txt
pvtk.egg-info/top_level.txt