Metadata-Version: 1.0
Name: pvtk
Version: 1.0
Summary: precipitation verification toolkit
Home-page: https://pypi.python.org/pypi/pvtk
Author: Fan Han
Author-email: hanfan5598@gmail.com
License: UNKNOWN
Platform: UNKNOWN
